{
    "type": "package",
    "name": "xdelph/elm-slick-grid",
    "summary": "Slick grid in ELM",
    "license": "BSD-3-Clause",
    "version": "1.1.0",
    "exposed-modules": [
        "Grid",
        "Grid.Colors",
        "Grid.Filters",
        "Grid.Parsers"
    ],
    "elm-version": "0.19.0 <= v < 0.20.0",
    "dependencies": {
        "FabienHenon/elm-infinite-list-view": "3.0.0 <= v < 4.0.0",
        "elm/core": "1.0.0 <= v < 2.0.0",
        "elm/html": "1.0.0 <= v < 2.0.0",
        "elm/parser": "1.0.0 <= v < 2.0.0",
        "elm-community/list-extra": "8.0.0 <= v < 9.0.0",
        "rtfeldman/elm-css": "16.0.0 <= v < 17.0.0"
    },
    "test-dependencies": {}
}
